sentipy/__init__.py
sentipy/fapar.py
sentipy/lib/__init__.py
sentipy/lib/activations.py
sentipy/lib/neuralnet.py
sentipy/lib/preprocessing.py
sentipy/settings.py
sentipy-0.1.0.dist-info/LICENSE
sentipy-0.1.0.dist-info/WHEEL
sentipy-0.1.0.dist-info/METADATA
sentipy-0.1.0.dist-info/RECORD
