Metadata-Version: 2.1
Name: sentipy
Version: 0.1.0
Summary: 
Author: UpstatePedro
Requires-Python: >=3.6,<4.0
Classifier: Programming Language :: Python :: 3
Classifier: Programming Language :: Python :: 3.6
Classifier: Programming Language :: Python :: 3.7
Classifier: Programming Language :: Python :: 3.8
Requires-Dist: numpy (>=1.18.4,<2.0.0)
